Workbook

Sheet Sheet1
B3: 1 | C3: Raw material | E3: 2 | F3: packaging | H3: 3 | I3: maintenance | K3: 4 | L3: car expenses | N3: 5 | O3: Car Rental and transportation
B4: 1-A | C4: Food ingredients | E4: 2-A | F4: Takeaway boxes | H4: 3-A | I4: Kitchen Equipment Maintenance | K4: 4-A | L4: Car maintenance | N4: 5-A | O4: car rent
C5: Meat | F5: Cups | I5: Building Maintenance | L5: Oil changes
C6: Chicken | F6: Lids | I6: Electrical Repairs | L6: Tire replacement and repairs | N6: 5-B | O6: Fuel Expense
C7: Fish & seafood | F7: Bags | I7: Plumbing Repairs | L7: Brake repairs
C8: Vegetables & fruits | F8: Napkins | I8: (A/C) Maintenance | L8: Battery replacement | N8: 5-C | O8: Transportation
C9: Rice, flour, pasta | F9: Disposable cutlery | I9: Furniture Repairs | L9: Engine repairs | O9: Parking Fees
C10: Dairy products | I10: pest control | L10: Regular servicing | O10: Delivery Vehicle Expenses
C11: Spices & seasonings | E11: 2-B | F11: Floor cleaner | I11: fire alarm | L11: Car wash (if expensed) | O11: Uber
F12: Dishwashing liquid | L12: Vehicle spare parts | O12: Freight and Local Transport
B13: 1-B | C13: Beverages | F13: Kitchen degreaser
C14: Soft drinks | F14: Bathroom cleaner | K14: 4-B | L14: Vehicle Insurance
C15: Juices | F15: Mops, brooms, brushes
C16: Coffee & tea | F16: Trash bags | K16: 4-C | L16: Vehicle Registration
C17: Water | F17: Hand soap
B19: 6 | C19: Direct expenses | E19: 7 | F19: Rent | H19: 8 | I19: Salaries | K19: 9 | L19: Bonus and allowance | N19: 10 | O19: Marketing
B20: 6-A | C20: Cooking gas | F20: Restaurant rent | H20: 8-A | I20: Management salaries | K20: 9-A | L20: Overtime | N20: 10-A | O20: Marketing & Advertising Expenses
F21: Kitchen rent | O21: Online Advertising
B22: 6-B | C22: Charcoal for grills/BBQ | F22: Storage/warehouse rent | K22: 9- B | L22: Bonus | O22: Social Media Marketing
F23: Office rent | H23: 8-B | I23: Admin staff salaries | O23: Promotions
K24: 9-C | L24: Allowances | O24: Printing & Design
L25: Housing Allowance | O25: Campaign Expenses
H26: 8-C | I26: Accounting/office salaries | L26: Transportation Allowance
L27: Meal Allowance
L28: Other Staff Allowances
B30: 11 | C30: Kahrama | E30: 12 | F30: Bank charge | H30: 13 | I30: stationery | K30: 14 | L30: Utilities | N30: 15 | O30: Government fees
B31: 11-A | C31: Electricity Expense | F31: Bank account fees | H31: 13-A | I31: Stationery Expense | K31: 14-A | L31: Mobile phone bills | O31: License Fees
F32: POS machine fees | O32: Permit Fees
B33: 11-B | C33: Water Expense | F33: Transfer fees | H33: 13-B | I33: Office Supplies | K33: 14-B | L33: Internet bills | O33: Municipality Fees
F34: Cheque fees | O34: Other Government Charges
F35: Other bank service charges | H35: 13-C | I35: Printing Expense | K35: 14-C | L35: Landline bills
F36: interest loan
B38: 16 | C38: Ticket and Traveling | E38: 17 | F38: Professional Fees | H38: 18 | I38: office expenses | K38: 19 | L38: Other Expenses ( indirect )
C39: Travel & Transportation | F39: Financial Consulting Fees | I39: Office Furniture (small purchases) | L39: Small business expenses not classified elsewhere
C40: Air Ticket Expense | F40: Legal Consulting Fees | L40: Gifts & Appreciation
C41: Hotel Expense | F41: Accounting Fees | I41: Software & Subscriptions | L41: Other unusual expenses
C42: Business Travel Expense | F42: Audit Fees | L42: Emergency Expenses
C43: Local Transport Expense | F43: Tax Consultancy Fees | I43: Office Maintenance | L43: Losses on disposal of assets
F44: Lawyer Fees | L44: Customer Compensation
F45: Business Advisory Fees | I45: Office Cleaning | L45: Donations
L46: Staff Events & Activities

Sheet July 2026
B1: =SUM(C137:AG137) -> 149692.73 | C1: 46204
A2: 1 | B2: Raw material | C2: 46204 | D2: 46205 | E2: 46206 | F2: 46207 | G2: 46208 | H2: 46209 | I2: 46210 | J2: 46211 | K2: 46212 | L2: 46213 | M2: 46214 | N2: 46215 | O2: 46216 | P2: 46217 | Q2: 46218 | R2: 46219 | S2: 46220 | T2: 46221 | U2: 46222 | V2: 46223 | W2: 46224 | X2: 46225 | Y2: 46226 | Z2: 46227 | AA2: 46228 | AB2: 46229 | AC2: 46230 | AD2: 46231 | AE2: 46232 | AF2: 46233 | AG2: 46234
A3: 1-A | B3: Food ingredients | C3: =94+21+43+20+22+5+156+100+723 -> 1184 | D3: =58+77+299+5+35+129+80+710+377+122+680+633+34 -> 3239 | E3: =24+70+69+59+5+20+150 -> 397 | F3: =20+4+225+1327+478+662 -> 2716 | G3: =36+580+246+231+107 -> 1200 | H3: =6625+595+20+20+311+125+124+661+660+72+139 -> 9352 | I3: =68+74+57+68+800 -> 1067 | J3: =270+57+150+169+40 -> 686 | K3: =172+32.4+225 -> 429.4 | L3: 34 | M3: =70+119+17+413+325+162+64+94+539+265+379 -> 2447 | N3: =32+120 -> 152 | O3: =170+357.5 -> 527.5 | P3: =152+5+120 -> 277 | Q3: =20+82+15+103.64+14 -> 234.64 | R3: =10+155+79.25+215.76+110 -> 570.01 | S3: 101.5 | T3: =69.5+120.75+30+53.5+212.75+308 -> 794.5 | U3: =53.25+28.5 -> 81.75 | V3: =30+18 -> 48 | W3: =25+1530+70+56.5+125 -> 1806.5 | X3: =58+56.25+10.5+19.5+224+1317 -> 1685.25 | Y3: =12+24+41+504 -> 581 | AA3: =20+105.86+233.6+95.88+135 -> 590.34 | AB3: =26+139+56+160+85+132.98 -> 598.98 | AC3: 112 | AD3: =80+46+38.5+182 -> 346.5 | AE3: =120+50+107.45+24+150+90+280+38.25+1408+917 -> 3184.7 | AF3: =47+10.5+55+340 -> 452.5 | AG3: 55 | AH3: =SUM(C3:AG3) -> 34951.07
B4: Meat | N4: 787.02 | U4: 513.5 | W4: 602.32 | Y4: 331.55 | AC4: 230 | AH4: =SUM(C4:AG4) -> 2464.39
B5: Chicken | W5: 1320 | AC5: 155 | AH5: =SUM(C5:AG5) -> 1475
B6: Fish & seafood | N6: 660 | AH6: =SUM(C6:AG6) -> 660
B7: Vegetables & fruits | F7: 3000 | M7: 4000 | AH7: =SUM(C7:AG7) -> 7000
B8: Rice, flour, pasta | AH8: =SUM(C8:AG8) -> 0
B9: Dairy products | AH9: =SUM(C9:AG9) -> 0
B10: Spices & seasonings | AH10: =SUM(C10:AG10) -> 0
A11: 1-B | B11: Beverages | AH11: =SUM(C11:AG11) -> 0
B12: Soft drinks | C12: 975 | AC12: 823 | AH12: =SUM(C12:AG12) -> 1798
B13: Juices | AH13: =SUM(C13:AG13) -> 0
B14: Coffee & tea | AH14: =SUM(C14:AG14) -> 0
B15: Water | C15: 450 | AH15: =SUM(C15:AG15) -> 450
A16: 2 | B16: packaging | D16: =52+138 -> 190 | H16: 299 | K16: =115+131+48.5+38+65+10 -> 407.5 | L16: =66 -> 66 | N16: 70 | Q16: =158+65+140 -> 363 | R16: 205 | W16: =50+93.5 -> 143.5 | AC16: 309 | AD16: 185 | AF16: 3 | AH16: =SUM(C16:AG16) -> 2241
A17: 2-A | B17: Takeaway boxes | AH17: =SUM(C17:AG17) -> 0
B18: Cups | Z18: 20 | AH18: =SUM(C18:AG18) -> 20
B19: Lids | AH19: =SUM(C19:AG19) -> 0
B20: Bags | AH20: =SUM(C20:AG20) -> 0
B21: Napkins | AH21: =SUM(C21:AG21) -> 0
B22: Disposable cutlery | AH22: =SUM(C22:AG22) -> 0
A23: 2-B | B23: Floor cleaner | AD23: 260 | AH23: =SUM(C23:AG23) -> 260
B24: Dishwashing liquid | AH24: =SUM(C24:AG24) -> 0
B25: Kitchen degreaser | AH25: =SUM(C25:AG25) -> 0
B26: Bathroom cleaner | AH26: =SUM(C26:AG26) -> 0
B27: Mops, brooms, brushes | AH27: =SUM(C27:AG27) -> 0
B28: Trash bags | AH28: =SUM(C28:AG28) -> 0
B29: Hand soap | AH29: =SUM(C29:AG29) -> 0
A30: 3 | B30: maintenance | AH30: =SUM(C30:AG30) -> 0
A31: 3-A | B31: Kitchen Equipment Maintenance | M31: 10 | AE31: 12 | AH31: =SUM(C31:AG31) -> 22
B32: Building Maintenance | C32: 1000 | AH32: =SUM(C32:AG32) -> 1000
B33: Electrical Repairs | AH33: =SUM(C33:AG33) -> 0
B34: Plumbing Repairs | AH34: =SUM(C34:AG34) -> 0
B35: (A/C) Maintenance | AH35: =SUM(C35:AG35) -> 0
B36: Furniture Repairs | AD36: 75 | AH36: =SUM(C36:AG36) -> 75
B37: pest control | D37: 1150 | AH37: =SUM(C37:AG37) -> 1150
B38: fire alarm | AH38: =SUM(C38:AG38) -> 0
A39: 4 | B39: car expenses | AH39: =SUM(C39:AG39) -> 0
A40: 4-A | B40: Car maintenance | P40: 1160 | AA40: =350+350+280+290 -> 1270 | AE40: 100 | AH40: =SUM(C40:AG40) -> 2530
B41: Oil changes | I41: 175 | AH41: =SUM(C41:AG41) -> 175
B42: Tire replacement and repairs | AH42: =SUM(C42:AG42) -> 0
B43: Brake repairs | AH43: =SUM(C43:AG43) -> 0
B44: Battery replacement | AH44: =SUM(C44:AG44) -> 0
B45: Engine repairs | AH45: =SUM(C45:AG45) -> 0
B46: Regular servicing | AH46: =SUM(C46:AG46) -> 0
B47: Car wash (if expensed) | W47: 35 | AA47: 30 | AH47: =SUM(C47:AG47) -> 65
B48: Vehicle spare parts | AH48: =SUM(C48:AG48) -> 0
A49: 4-B | B49: Vehicle Insurance | AH49: =SUM(C49:AG49) -> 0
A50: 4-C | B50: Vehicle Registration | AH50: =SUM(C50:AG50) -> 0
A51: 5 | B51: Car Rental and transportation | AH51: =SUM(C51:AG51) -> 0
A52: 5-A | B52: car rent | F52: 2590 | I52: 1600 | AH52: =SUM(C52:AG52) -> 4190
A53: 5-B | B53: Fuel Expense | C53: =64+65+70+164 -> 363 | D53: =75+73 -> 148 | F53: =75+50 -> 125 | G53: =75+70+193 -> 338 | H53: =73+65 -> 138 | I53: =70+80+68 -> 218 | J53: =173+75+77 -> 325 | K53: =80+73 -> 153 | L53: =80 -> 80 | M53: 77 | N53: =72+75+73 -> 220 | O53: =71 -> 71 | P53: =75+186+50 -> 311 | Q53: =65+85 -> 150 | R53: 63 | T53: =85+77+194 -> 356 | U53: 80 | V53: =70+83 -> 153 | W53: =85 -> 85 | X53: =70+81+80 -> 231 | Y53: =83+75+73 -> 231 | Z53: =30 -> 30 | AA53: =85+78 -> 163 | AB53: =69+70+193 -> 332 | AC53: =81+60 -> 141 | AD53: =74+85 -> 159 | AE53: =82+73.27 -> 155.27 | AF53: =85+60 -> 145 | AH53: =SUM(C53:AG53) -> 5041.27
A54: 5-C | B54: Transportation | AH54: =SUM(C54:AG54) -> 0
B55: Parking Fees | AH55: =SUM(C55:AG55) -> 0
B56: Delivery Vehicle Expenses | AH56: =SUM(C56:AG56) -> 0
B57: Uber | AH57: =SUM(C57:AG57) -> 0
B58: Freight and Local Transport | AH58: =SUM(C58:AG58) -> 0
A59: 6 | B59: Direct expenses | AH59: =SUM(C59:AG59) -> 0
A60: 6-A | B60: Cooking gas | D60: 90 | H60: 90 | I60: 60 | V60: =30+45 -> 75 | AA60: 90 | AE60: 30 | AH60: =SUM(C60:AG60) -> 435
A61: 6-B | B61: Charcoal for grills/BBQ | C61: 250 | N61: 250 | V61: 500 | AH61: =SUM(C61:AG61) -> 1000
A62: 7 | B62: Rent | AH62: =SUM(C62:AG62) -> 0
B63: Restaurant rent | AH63: =SUM(C63:AG63) -> 0
B64: Kitchen rent | AH64: =SUM(C64:AG64) -> 0
B65: Storage/warehouse rent | K65: 20000 | AH65: =SUM(C65:AG65) -> 20000
B66: Office rent | C66: 2200 | AH66: =SUM(C66:AG66) -> 2200
A67: 8 | B67: Salaries | AH67: =SUM(C67:AG67) -> 0
A68: 8-A | B68: Management salaries | H68: 1000 | L68: 1000 | N68: 111.5 | Q68: 5000 | AC68: 11000 | AH68: =SUM(C68:AG68) -> 18111.5
A69: 8-B | B69: Admin staff salaries | H69: 1200 | K69: 7300 | P69: 50 | S69: 800 | V69: 1200 | Z69: 500 | AC69: =200+100 -> 300 | AH69: =SUM(C69:AG69) -> 11350
A70: 8-C | B70: Accounting/office salaries | I70: 200 | V70: =720+500+2160 -> 3380 | AH70: =SUM(C70:AG70) -> 3580
A71: 9 | B71: Bonus and allowance | AH71: =SUM(C71:AG71) -> 0
A72: 9-A | B72: Overtime | AH72: =SUM(C72:AG72) -> 0
A73: 9- B | B73: Bonus | AH73: =SUM(C73:AG73) -> 0
A74: 9-C | B74: Allowances | AH74: =SUM(C74:AG74) -> 0
B75: Housing Allowance | G75: 2600 | K75: 1553 | AH75: =SUM(C75:AG75) -> 4153
B76: Transportation Allowance | AH76: =SUM(C76:AG76) -> 0
B77: Meal Allowance | AH77: =SUM(C77:AG77) -> 0
B78: Other Staff Allowances | AH78: =SUM(C78:AG78) -> 0
A79: 10 | B79: Marketing | D79: =20*3.65 -> 73 | AH79: =SUM(C79:AG79) -> 73
A80: 10-A | B80: Marketing & Advertising Expenses | C80: 100 | D80: 100 | E80: 50 | F80: 50 | G80: 50 | AB80: 6500 | AH80: =SUM(C80:AG80) -> 6850
B81: Online Advertising | AH81: =SUM(C81:AG81) -> 0
B82: Social Media Marketing | AH82: =SUM(C82:AG82) -> 0
B83: Promotions | AH83: =SUM(C83:AG83) -> 0
B84: Printing & Design | AH84: =SUM(C84:AG84) -> 0
B85: Campaign Expenses | AH85: =SUM(C85:AG85) -> 0
A86: 11 | B86: Kahrama | AF86: 7062 | AH86: =SUM(C86:AG86) -> 7062
A87: 11-A | B87: Electricity Expense | AH87: =SUM(C87:AG87) -> 0
A88: 11-B | B88: Water Expense | AH88: =SUM(C88:AG88) -> 0
A89: 12 | B89: Bank charge | AH89: =SUM(C89:AG89) -> 0
B90: Bank account fees | AH90: =SUM(C90:AG90) -> 0
B91: POS machine fees | AH91: =SUM(C91:AG91) -> 0
B92: Transfer fees | AH92: =SUM(C92:AG92) -> 0
B93: Cheque fees | AH93: =SUM(C93:AG93) -> 0
B94: Other bank service charges | AH94: =SUM(C94:AG94) -> 0
B95: interest loan | AH95: =SUM(C95:AG95) -> 0
A96: 13 | B96: stationery | AH96: =SUM(C96:AG96) -> 0
A97: 13-A | B97: Stationery Expense | AH97: =SUM(C97:AG97) -> 0
A98: 13-B | B98: Office Supplies | D98: 182 | AH98: =SUM(C98:AG98) -> 182
A99: 13-C | B99: Printing Expense | AH99: =SUM(C99:AG99) -> 0
A100: 14 | B100: Utilities | AH100: =SUM(C100:AG100) -> 0
...

Sheet Aug 2026
B1: =SUM(C154:AG154) -> 129385.29 | C1: 46235 | D1: 46236 | E1: 46237 | F1: 46238 | G1: 46239 | H1: 46240 | I1: 46241 | J1: 46242 | K1: 46243 | L1: 46244 | M1: 46245 | N1: 46246 | O1: 46247 | P1: 46248 | Q1: 46249 | R1: 46250 | S1: 46251 | T1: 46252 | U1: 46253 | V1: 46254 | W1: 46255 | X1: 46256 | Y1: 46257 | Z1: 46258 | AA1: 46259 | AB1: 46260 | AC1: 46261 | AD1: 46262 | AE1: 46263 | AF1: 46264 | AG1: 46265
A2: 1 | B2: Raw material | C2: =SUM(C3:C15) -> 1382.63 | D2: =SUM(D3:D15) -> 3663.54 | E2: =SUM(E3:E15) -> 2657.32 | F2: =SUM(F3:F15) -> 4816 | G2: =SUM(G3:G15) -> 1287.92 | H2: =SUM(H3:H15) -> 3450.6 | I2: =SUM(I3:I15) -> 34.75 | J2: =SUM(J3:J15) -> 938.22 | ... AG2: =SUM(AG3:AG15) -> 0 | AH2: =SUM(C2:AG2) -> 22795.49
A3: 1-A | B3: Food ingredients | C3: =110.68+407+99.75+30+164.85+163.35+57 -> 1032.63 | D3: =224+115+413.5+500+96+18 -> 1366.5 | E3: =32.89+443.7+20.25+9.28+2151.2 -> 2657.32 | F3: =16+30+10+760 -> 816 | G3: =5+37+450+12+506.92+96+16+31+39+95 -> 1287.92 | H3: =75+40+23+20+247.6+95+2950 -> 3450.6 | I3: 34.75 | J3: =515+35.09+20+182.13+186 -> 938.22 | K3: =68.68+35.32+30+415 -> 549 | L3: =28+25.5+95.78+48 -> 197.28 | M3: =130+76.75 -> 206.75 | N3: =46+49.25+224+120+124+950 -> 1513.25 | O3: =16.6+155.38+82.95+42.3+303.05+23.25+35 -> 658.53 | Q3: =30+26.5+52.5+149.65+760.5 -> 1019.15 | R3: =10 -> 10 | AH3: =SUM(C3:AG3) -> 15737.9
B4: Meat | D4: =2131.04+132 -> 2263.04 | L4: 184 | M4: 226.55 | AH4: =SUM(C4:AG4) -> 2673.59
B5: Chicken | AH5: =SUM(C5:AG5) -> 0
B6: Fish & seafood | AH6: =SUM(C6:AG6) -> 0
B7: Vegetables & fruits | D7: 34 | F7: 4000 | AH7: =SUM(C7:AG7) -> 4034
B8: Rice, flour, pasta | AH8: =SUM(C8:AG8) -> 0
B9: Dairy products | C9: 350 | AH9: =SUM(C9:AG9) -> 350
B10: Spices & seasonings | AH10: =SUM(C10:AG10) -> 0
A11: 1-B | B11: Beverages | AH11: =SUM(C11:AG11) -> 0
B12: Soft drinks | AH12: =SUM(C12:AG12) -> 0
B13: Juices | AH13: =SUM(C13:AG13) -> 0
B14: Coffee & tea | AH14: =SUM(C14:AG14) -> 0
B15: Water | AH15: =SUM(C15:AG15) -> 0
C16: =SUM(C17:C30) -> 0 | D16: =SUM(D17:D30) -> 0 | E16: =SUM(E17:E30) -> 0 | F16: =SUM(F17:F30) -> 6028 | G16: =SUM(G17:G30) -> 0 | H16: =SUM(H17:H30) -> 0 | I16: =SUM(I17:I30) -> 0 | J16: =SUM(J17:J30) -> 0 | ... AG16: =SUM(AG17:AG30) -> 0 | AH16: =SUM(C16:AG16) -> 7158
A17: 2 | B17: packaging | F17: =1398+5+4625 -> 6028 | K17: =145+230+41 -> 416 | L17: =50+185+138+21 -> 394 | N17: 110 | P17: 90 | Q17: =100+20 -> 120 | AH17: =SUM(C17:AG17) -> 7158
A18: 2-A | B18: Takeaway boxes | AH18: =SUM(C18:AG18) -> 0
B19: Cups | AH19: =SUM(C19:AG19) -> 0
B20: Lids | AH20: =SUM(C20:AG20) -> 0
B21: Bags | AH21: =SUM(C21:AG21) -> 0
B22: Napkins | AH22: =SUM(C22:AG22) -> 0
B23: Disposable cutlery | AH23: =SUM(C23:AG23) -> 0
A24: 2-B | B24: Floor cleaner | AH24: =SUM(C24:AG24) -> 0
B25: Dishwashing liquid | AH25: =SUM(C25:AG25) -> 0
B26: Kitchen degreaser | AH26: =SUM(C26:AG26) -> 0
B27: Bathroom cleaner | AH27: =SUM(C27:AG27) -> 0
B28: Mops, brooms, brushes | AH28: =SUM(C28:AG28) -> 0
B29: Trash bags | AH29: =SUM(C29:AG29) -> 0
B30: Hand soap | AH30: =SUM(C30:AG30) -> 0
C31: =SUM(C32:C40) -> 0 | D31: =SUM(D32:D40) -> 0 | E31: =SUM(E32:E40) -> 0 | F31: =SUM(F32:F40) -> 800 | G31: =SUM(G32:G40) -> 0 | H31: =SUM(H32:H40) -> 0 | I31: =SUM(I32:I40) -> 0 | J31: =SUM(J32:J40) -> 0 | ... AG31: =SUM(AG32:AG40) -> 0 | AH31: =SUM(C31:AG31) -> 1297
A32: 3 | B32: maintenance | AH32: =SUM(C32:AG32) -> 0
A33: 3-A | B33: Kitchen Equipment Maintenance | F33: 800 | O33: =7+25 -> 32 | AH33: =SUM(C33:AG33) -> 832
B34: Building Maintenance | K34: 465 | AH34: =SUM(C34:AG34) -> 465
B35: Electrical Repairs | AH35: =SUM(C35:AG35) -> 0
B36: Plumbing Repairs | AH36: =SUM(C36:AG36) -> 0
B37: (A/C) Maintenance | AH37: =SUM(C37:AG37) -> 0
B38: Furniture Repairs | AH38: =SUM(C38:AG38) -> 0
B39: pest control | AH39: =SUM(C39:AG39) -> 0
B40: fire alarm | AH40: =SUM(C40:AG40) -> 0
C41: =SUM(C42:C53) -> 25 | D41: =SUM(D42:D53) -> 0 | E41: =SUM(E42:E53) -> 0 | F41: =SUM(F42:F53) -> 0 | G41: =SUM(G42:G53) -> 0 | H41: =SUM(H42:H53) -> 0 | I41: =SUM(I42:I53) -> 0 | J41: =SUM(J42:J53) -> 0 | ... AG41: =SUM(AG42:AG53) -> 0 | AH41: =SUM(C41:AG41) -> 1405
A42: 4 | B42: car expenses | AH42: =SUM(C42:AG42) -> 0
A43: 4-A | B43: Car maintenance | N43: =650+300 -> 950 | AH43: =SUM(C43:AG43) -> 950
B44: Oil changes | AH44: =SUM(C44:AG44) -> 0
B45: Tire replacement and repairs | Q45: 430 | AH45: =SUM(C45:AG45) -> 430
B46: Brake repairs | AH46: =SUM(C46:AG46) -> 0
B47: Battery replacement | AH47: =SUM(C47:AG47) -> 0
B48: Engine repairs | AH48: =SUM(C48:AG48) -> 0
B49: Regular servicing | AH49: =SUM(C49:AG49) -> 0
B50: Car wash (if expensed) | C50: 25 | AH50: =SUM(C50:AG50) -> 25
B51: Vehicle spare parts | AH51: =SUM(C51:AG51) -> 0
A52: 4-B | B52: Vehicle Insurance | AH52: =SUM(C52:AG52) -> 0
A53: 4-C | B53: Vehicle Registration | AH53: =SUM(C53:AG53) -> 0
C54: =SUM(C55:C62) -> 130 | D54: =SUM(D55:D62) -> 216 | E54: =SUM(E55:E62) -> 81 | F54: =SUM(F55:F62) -> 354 | G54: =SUM(G55:G62) -> 2812 | H54: =SUM(H55:H62) -> 80 | I54: =SUM(I55:I62) -> 71 | J54: =SUM(J55:J62) -> 1670 | ... AG54: =SUM(AG55:AG62) -> 0 | AH54: =SUM(C54:AG54) -> 6872.53
A55: 5 | B55: Car Rental and transportation | AH55: =SUM(C55:AG55) -> 0
A56: 5-A | B56: car rent | G56: 2590 | J56: 1600 | AH56: =SUM(C56:AG56) -> 4190
A57: 5-B | B57: Fuel Expense | C57: =80+50 -> 130 | D57: =75+69+72 -> 216 | E57: =81 -> 81 | F57: =204+70+80 -> 354 | G57: =77+75+70 -> 222 | H57: 80 | I57: 71 | J57: 70 | K57: =75+79 -> 154 | L57: =90.42+187.01+73 -> 350.43 | M57: =74+76 -> 150 | N57: =68+70+85 -> 223 | O57: 80 | Q57: =74+87.01 -> 161.01 | R57: =190.09+65+85 -> 340.09 | AH57: =SUM(C57:AG57) -> 2682.53
A58: 5-C | B58: Transportation | AH58: =SUM(C58:AG58) -> 0
B59: Parking Fees | AH59: =SUM(C59:AG59) -> 0
B60: Delivery Vehicle Expenses | AH60: =SUM(C60:AG60) -> 0
B61: Uber | AH61: =SUM(C61:AG61) -> 0
B62: Freight and Local Transport | AH62: =SUM(C62:AG62) -> 0
C63: =SUM(C64:C66) -> 250 | D63: =SUM(D64:D66) -> 75 | E63: =SUM(E64:E66) -> 0 | F63: =SUM(F64:F66) -> 0 | G63: =SUM(G64:G66) -> 0 | H63: =SUM(H64:H66) -> 0 | I63: =SUM(I64:I66) -> 0 | J63: =SUM(J64:J66) -> 75 | ... AG63: =SUM(AG64:AG66) -> 0 | AH63: =SUM(C63:AG63) -> 1240
A64: 6 | B64: Direct expenses | AH64: =SUM(C64:AG64) -> 0
A65: 6-A | B65: Cooking gas | D65: 75 | J65: 75 | N65: 45 | R65: 45 | AH65: =SUM(C65:AG65) -> 240
A66: 6-B | B66: Charcoal for grills/BBQ | C66: 250 | M66: 750 | AH66: =SUM(C66:AG66) -> 1000
C67: =SUM(C68:C72) -> 0 | D67: =SUM(D68:D72) -> 0 | E67: =SUM(E68:E72) -> 0 | F67: =SUM(F68:F72) -> 0 | G67: =SUM(G68:G72) -> 2200 | H67: =SUM(H68:H72) -> 0 | I67: =SUM(I68:I72) -> 0 | J67: =SUM(J68:J72) -> 0 | ... AG67: =SUM(AG68:AG72) -> 0 | AH67: =SUM(C67:AG67) -> 12200
A68: 7 | B68: Rent | AH68: =SUM(C68:AG68) -> 0
B69: Restaurant rent | N69: 10000 | AH69: =SUM(C69:AG69) -> 10000
B70: Kitchen rent | AH70: =SUM(C70:AG70) -> 0
B71: Storage/warehouse rent | G71: 2200 | AH71: =SUM(C71:AG71) -> 2200
B72: Office rent | AH72: =SUM(C72:AG72) -> 0
C73: =SUM(C74:C85) -> 200 | D73: =SUM(D74:D85) -> 700 | E73: =SUM(E74:E85) -> 0 | F73: =SUM(F74:F85) -> 6000 | G73: =SUM(G74:G85) -> 40335 | H73: =SUM(H74:H85) -> 4750 | I73: =SUM(I74:I85) -> 0 | J73: =SUM(J74:J85) -> 250 | ... AG73: =SUM(AG74:AG85) -> 0 | AH73: =SUM(C73:AG73) -> 68935
A74: 8 | B74: Salaries | N74: 4000 | Q74: 1500 | AH74: =SUM(C74:AG74) -> 5500
A75: 8-A | B75: Management salaries | F75: 6000 | G75: 20000 | H75: 2750 | M75: 2500 | N75: =2600+6000+100 -> 8700 | AH75: =SUM(C75:AG75) -> 39950
A76: 8-B | B76: Admin staff salaries | C76: =200 -> 200 | D76: 700 | G76: =1450+1450+2780+3500+1400+2650+1750+1400+1400+2555 -> 20335 | H76: 2000 | J76: 250 | AH76: =SUM(C76:AG76) -> 23485
A77: 8-C | B77: Accounting/office salaries | AH77: =SUM(C77:AG77) -> 0
A78: 9 | B78: Bonus and allowance | AH78: =SUM(C78:AG78) -> 0
A79: 9-A | B79: Overtime | AH79: =SUM(C79:AG79) -> 0
A80: 9- B | B80: Bonus | AH80: =SUM(C80:AG80) -> 0
A81: 9-C | B81: Allowances | AH81: =SUM(C81:AG81) -> 0
B82: Housing Allowance | AH82: =SUM(C82:AG82) -> 0
B83: Transportation Allowance | AH83: =SUM(C83:AG83) -> 0
B84: Meal Allowance | AH84: =SUM(C84:AG84) -> 0
B85: Other Staff Allowances | AH85: =SUM(C85:AG85) -> 0
C86: =SUM(C87:C93) -> 0 | D86: =SUM(D87:D93) -> 0 | E86: =SUM(E87:E93) -> 0 | F86: =SUM(F87:F93) -> 0 | G86: =SUM(G87:G93) -> 0 | H86: =SUM(H87:H93) -> 0 | I86: =SUM(I87:I93) -> 0 | J86: =SUM(J87:J93) -> 0 | ... AG86: =SUM(AG87:AG93) -> 0 | AH86: =SUM(C86:AG86) -> 1116.56
A87: 10 | B87: Marketing | AH87: =SUM(C87:AG87) -> 0
A88: 10-A | B88: Marketing & Advertising Expenses | AH88: =SUM(C88:AG88) -> 0
B89: Online Advertising | AH89: =SUM(C89:AG89) -> 0
B90: Social Media Marketing | M90: 1116.56 | AH90: =SUM(C90:AG90) -> 1116.56
B91: Promotions | AH91: =SUM(C91:AG91) -> 0
B92: Printing & Design | AH92: =SUM(C92:AG92) -> 0
B93: Campaign Expenses | AH93: =SUM(C93:AG93) -> 0
C94: =SUM(C95:C97) -> 0 | D94: =SUM(D95:D97) -> 0 | E94: =SUM(E95:E97) -> 0 | F94: =SUM(F95:F97) -> 0 | G94: =SUM(G95:G97) -> 0 | H94: =SUM(H95:H97) -> 0 | I94: =SUM(I95:I97) -> 0 | J94: =SUM(J95:J97) -> 0 | ... AG94: =SUM(AG95:AG97) -> 0 | AH94: =SUM(C94:AG94) -> 0
A95: 11 | B95: Kahrama | AH95: =SUM(C95:AG95) -> 0
A96: 11-A | B96: Electricity Expense | AH96: =SUM(C96:AG96) -> 0
A97: 11-B | B97: Water Expense | AH97: =SUM(C97:AG97) -> 0
C98: =SUM(C99:C105) -> 0 | D98: =SUM(D99:D105) -> 0 | E98: =SUM(E99:E105) -> 0 | F98: =SUM(F99:F105) -> 0 | G98: =SUM(G99:G105) -> 0 | H98: =SUM(H99:H105) -> 0 | I98: =SUM(I99:I105) -> 0 | J98: =SUM(J99:J105) -> 0 | ... AG98: =SUM(AG99:AG105) -> 0 | AH98: =SUM(C98:AG98) -> 125.21
A99: 12 | B99: Bank charge | N99: 20 | AH99: =SUM(C99:AG99) -> 20
B100: Bank account fees | AH100: =SUM(C100:AG100) -> 0
...

Sheet Aug Cost Analysis
B1: COST ANALYSIS - PARETO
B2: Pareto Chart for Cumulative Percent of Annual Costs across all Cost Centers is in cells B2 through E3.
B4: COST ANALYSIS
B5: Cost Center | C5: Monthly Cost | D5: Percent of Total | E5: Cumulative Percent
A6: 1 | B6: Raw Material | C6: ='Aug 2026'!E167 -> 22795.49 | D6: =IFERROR(Data[[#This Row],[Monthly Cost ]]/SUM(Data[[Monthly Cost ]]), "") -> 0.17632639 | E6: =IFERROR(SUM(INDEX(Data[Percent of Total],1):Data[[#This Row],[Percent of Total]]), "") -> 0.17632639
A7: 2 | B7: Packaging | C7: ='Aug 2026'!E168 -> 7158 | D7: =IFERROR(Data[[#This Row],[Monthly Cost ]]/SUM(Data[[Monthly Cost ]]), "") -> 0.055368159 | E7: =IFERROR(SUM(INDEX(Data[Percent of Total],1):Data[[#This Row],[Percent of Total]]), "") -> 0.23169455
A8: 3 | B8: Maintenance | C8: ='Aug 2026'!E169 -> 1297 | D8: =IFERROR(Data[[#This Row],[Monthly Cost ]]/SUM(Data[[Monthly Cost ]]), "") -> 0.010032481 | E8: =IFERROR(SUM(INDEX(Data[Percent of Total],1):Data[[#This Row],[Percent of Total]]), "") -> 0.24172703
A9: 4 | B9: Car Expenses | C9: ='Aug 2026'!E170 -> 1405 | D9: =IFERROR(Data[[#This Row],[Monthly Cost ]]/SUM(Data[[Monthly Cost ]]), "") -> 0.010867877 | E9: =IFERROR(SUM(INDEX(Data[Percent of Total],1):Data[[#This Row],[Percent of Total]]), "") -> 0.25259491
A10: 5 | B10: Car Rental and transportation | C10: ='Aug 2026'!E171 -> 6872.53 | D10: =IFERROR(Data[[#This Row],[Monthly Cost ]]/SUM(Data[[Monthly Cost ]]), "") -> 0.053160007 | E10: =IFERROR(SUM(INDEX(Data[Percent of Total],1):Data[[#This Row],[Percent of Total]]), "") -> 0.30575492
A11: 6 | B11: Direct expenses | C11: ='Aug 2026'!E172 -> 1240 | D11: =IFERROR(Data[[#This Row],[Monthly Cost ]]/SUM(Data[[Monthly Cost ]]), "") -> 0.0095915782 | E11: =IFERROR(SUM(INDEX(Data[Percent of Total],1):Data[[#This Row],[Percent of Total]]), "") -> 0.31534649
A12: 7 | B12: Rent | C12: ='Aug 2026'!E173 -> 12200 | D12: =IFERROR(Data[[#This Row],[Monthly Cost ]]/SUM(Data[[Monthly Cost ]]), "") -> 0.094368753 | E12: =IFERROR(SUM(INDEX(Data[Percent of Total],1):Data[[#This Row],[Percent of Total]]), "") -> 0.40971525
A13: 8 | B13: Salaries | C13: ='Aug 2026'!E174 -> 68935 | D13: =IFERROR(Data[[#This Row],[Monthly Cost ]]/SUM(Data[[Monthly Cost ]]), "") -> 0.53322213 | E13: =IFERROR(SUM(INDEX(Data[Percent of Total],1):Data[[#This Row],[Percent of Total]]), "") -> 0.94293738
A14: 9 | B14: Bonus and Allowance | C14: ='Aug 2026'!E175 -> 0 | D14: =IFERROR(Data[[#This Row],[Monthly Cost ]]/SUM(Data[[Monthly Cost ]]), "") -> 0 | E14: =IFERROR(SUM(INDEX(Data[Percent of Total],1):Data[[#This Row],[Percent of Total]]), "") -> 0.94293738
A15: 10 | B15: Marketing | C15: ='Aug 2026'!E176 -> 1116.56 | D15: =IFERROR(Data[[#This Row],[Monthly Cost ]]/SUM(Data[[Monthly Cost ]]), "") -> 0.0086367521 | E15: =IFERROR(SUM(INDEX(Data[Percent of Total],1):Data[[#This Row],[Percent of Total]]), "") -> 0.95157413
A16: 11 | B16: Kahramaa | C16: ='Aug 2026'!E177 -> 0 | D16: =IFERROR(Data[[#This Row],[Monthly Cost ]]/SUM(Data[[Monthly Cost ]]), "") -> 0 | E16: =IFERROR(SUM(INDEX(Data[Percent of Total],1):Data[[#This Row],[Percent of Total]]), "") -> 0.95157413
A17: 12 | B17: Bank Charges | C17: ='Aug 2026'!E178 -> 20 | D17: =IFERROR(Data[[#This Row],[Monthly Cost ]]/SUM(Data[[Monthly Cost ]]), "") -> 0.00015470287 | E17: =IFERROR(SUM(INDEX(Data[Percent of Total],1):Data[[#This Row],[Percent of Total]]), "") -> 0.95172884
... A24: 19 | B24: Other Expenses ( indirect ) | C24: ='Aug 2026'!E185 -> 14 | D24: =IFERROR(Data[[#This Row],[Monthly Cost ]]/SUM(Data[[Monthly Cost ]]), "") -> 0.00010829201 | E24: =IFERROR(SUM(INDEX(Data[Percent of Total],1):Data[[#This Row],[Percent of Total]]), "") -> 1
C25: ='Aug 2026'!E186 -> 0 | D25: =IFERROR(Data[[#This Row],[Monthly Cost ]]/SUM(Data[[Monthly Cost ]]), "") -> 0 | E25: =IFERROR(SUM(INDEX(Data[Percent of Total],1):Data[[#This Row],[Percent of Total]]), "") -> 1
C26: ='Aug 2026'!E187 -> 0 | D26: =IFERROR(Data[[#This Row],[Monthly Cost ]]/SUM(Data[[Monthly Cost ]]), "") -> 0 | E26: =IFERROR(SUM(INDEX(Data[Percent of Total],1):Data[[#This Row],[Percent of Total]]), "") -> 1
B27: Total | C27: =SUBTOTAL(109,Data[[Monthly Cost ]]) -> 129280.08 | D27: =SUBTOTAL(109,Data[Percent of Total]) -> 1
